txtemo/__init__.py
txtemo/model.py
txtemo-0.1.0.dist-info/METADATA
txtemo-0.1.0.dist-info/WHEEL
txtemo-0.1.0.dist-info/top_level.txt
txtemo-0.1.0.dist-info/RECORD
