Metadata-Version: 2.4
Name: txtemo
Version: 0.1.0
Summary: ONNX-based emotion detection using quantized RoBERTa
Author: Pranesh S
Requires-Python: >=3.8
Requires-Dist: onnxruntime>=1.14.0
Requires-Dist: transformers>=4.30.0
Requires-Dist: huggingface_hub>=0.14.1
Requires-Dist: numpy
